CHANGES.txt
LICENSE.txt
MANIFEST.in
README.txt
setup.py
MicroApacheMonitor.egg-info/PKG-INFO
MicroApacheMonitor.egg-info/SOURCES.txt
MicroApacheMonitor.egg-info/dependency_links.txt
MicroApacheMonitor.egg-info/requires.txt
MicroApacheMonitor.egg-info/top_level.txt
bin/mapachemon_start.bat
bin/mapachemon_start.py
mapachemon/SysTrayIcon.py
mapachemon/__init__.py
mapachemon/mapachemon.py