Metadata-Version: 1.0
Name: MicroApacheMonitor
Version: 0.1c1
Summary: Windows system tray app for controlling MicroApache
Home-page: http://sourceforge.net/projects/mapachemonitor/
Author: James R. Cook
Author-email: cookjr@users.sourceforge.net
License: LICENSE.txt
Platform: UNKNOWN
